linktester/__init__.py
linktester/link.py
linktester/validation.py
linktester-0.0.3.data/scripts/linktester_client.py
linktester-0.0.3.dist-info/LICENSE
linktester-0.0.3.dist-info/METADATA
linktester-0.0.3.dist-info/WHEEL
linktester-0.0.3.dist-info/top_level.txt
linktester-0.0.3.dist-info/RECORD
