Metadata-Version: 2.1
Name: linktester
Version: 0.0.3
Summary: Simple client that checks a network link for common errors
Home-page: https://github.com/josevnz/linktester
Author: Jose Vicente Nunez Zuleta
Author-email: kodegeek.com@protonmail.com
License: Apache 2.0
License-File: LICENSE
Requires-Dist: rich
Requires-Dist: iperf3
Requires-Dist: importlib ; python_version == "3.9"
